_pypytest.py
pynary/__init__.py
pynary/decoder.py
pynary/encoder.py
pynary/pyn.py
pynary/pyn_blank.py
pynary/pynfunc.py
pynary-1.2.1.dist-info/LICENSE
pynary-1.2.1.dist-info/METADATA
pynary-1.2.1.dist-info/WHEEL
pynary-1.2.1.dist-info/top_level.txt
pynary-1.2.1.dist-info/RECORD
