Metadata-Version: 2.1
Name: pynary
Version: 1.2.1
Summary: Encode python objects as binary data in a (by default) safe way.
Author-email: myujiku <myu@myujiku.com>
Project-URL: Source, https://github.com/myu-jiku/pynary/
Classifier: Programming Language :: Python :: 3
Classifier: License :: OSI Approved :: GNU General Public License v3 or later (GPLv3+)
Classifier: Operating System :: OS Independent
Classifier: Intended Audience :: Developers
Requires-Python: >=3.7
License-File: LICENSE
